MANIFEST.in
README.rst
setup.py
django_dockitcms.egg-info/PKG-INFO
django_dockitcms.egg-info/SOURCES.txt
django_dockitcms.egg-info/dependency_links.txt
django_dockitcms.egg-info/top_level.txt
dockitcms/__init__.py
dockitcms/app_settings.py
dockitcms/clients.py
dockitcms/common.py
dockitcms/datataps.py
dockitcms/fields.py
dockitcms/listeners.py
dockitcms/middleware.py
dockitcms/mixins.py
dockitcms/scope.py
dockitcms/signals.py
dockitcms/sites.py
dockitcms/urls.py
dockitcms/utils.py
dockitcms/contrib/__init__.py
dockitcms/contrib/dockit_admin_tools/__init__.py
dockitcms/contrib/dockit_admin_tools/menu.py
dockitcms/contrib/dockit_admin_tools/modules.py
dockitcms/contrib/formviewpoint/__init__.py
dockitcms/contrib/formviewpoint/fields.py
dockitcms/contrib/formviewpoint/html5widgets.py
dockitcms/contrib/formviewpoint/models.py
dockitcms/contrib/thumbnailfield/__init__.py
dockitcms/contrib/thumbnailfield/fields.py
dockitcms/contrib/thumbnailfield/models.py
dockitcms/contrib/thumbnailfield/properties.py
dockitcms/loading/__init__.py
dockitcms/loading/base.py
dockitcms/loading/cache.py
dockitcms/models/__init__.py
dockitcms/models/collection.py
dockitcms/models/design.py
dockitcms/models/index.py
dockitcms/models/mixin.py
dockitcms/models/properties.py
dockitcms/models/view_point.py
dockitcms/pagecollection/__init__.py
dockitcms/pagecollection/models.py
dockitcms/pagecollection/resources.py
dockitcms/pagecollection/viewpoints.py
dockitcms/resources/__init__.py
dockitcms/resources/cms.py
dockitcms/resources/collection.py
dockitcms/resources/common.py
dockitcms/resources/listeners.py
dockitcms/resources/old_public.py
dockitcms/resources/public.py
dockitcms/resources/signals.py
dockitcms/resources/urls.py
dockitcms/resources/virtual.py
dockitcms/templates/admin/dockitcms/viewpoint/change_form.html
dockitcms/templates/dockitcms/base.html
dockitcms/templates/dockitcms/detail.html
dockitcms/templates/dockitcms/list.html
dockitcms/templates/dockitcms/mixin_object_tool.html
dockitcms/templates/dockitcms/scaffold/field.html
dockitcms/templates/dockitcms/scaffold/image.html
dockitcms/templates/dockitcms/scaffold/list.html
