Metadata-Version: 1.1
Name: django-dockitcms
Version: 0.0.11
Summary: CMS written using django-dockit
Home-page: http://github.com/webcube/django-dockitcms
Author: Jason Kraus
Author-email: zbyte64@gmail.com
License: New BSD License
Keywords: django CMS
Platform: UNKNOWN
Classifier: Programming Language :: Python
Classifier: Operating System :: OS Independent
Classifier: Natural Language :: English
Classifier: Development Status :: 3 - Alpha
Classifier: Intended Audience :: Developers
Classifier: Topic :: Internet :: WWW/HTTP :: Dynamic Content
